setup.py
suhani_distribution/Binomialdistribution.py
suhani_distribution/Gaussiandistribution.py
suhani_distribution/Generaldistribution.py
suhani_distribution/__init__.py
suhani_distribution.egg-info/PKG-INFO
suhani_distribution.egg-info/SOURCES.txt
suhani_distribution.egg-info/dependency_links.txt
suhani_distribution.egg-info/not-zip-safe
suhani_distribution.egg-info/top_level.txt