Metadata-Version: 1.0
Name: suhani-distribution
Version: 1.0
Summary: Gaussian distributions
Home-page: UNKNOWN
Author: Suhani
Author-email: UNKNOWN
License: UNKNOWN
Platform: UNKNOWN
